{
  "meta": {
    "tracker_name": "PS5 and TV Deal Tracker",
    "purchase_area": "Big-box retailers and Houston-area pickup/delivery",
    "blocker": null
  },
  "refresh": {
    "data_refreshed_at_utc": "2026-07-21T11:04:07Z",
    "last_attempt_at_utc": "2026-07-21T11:04:44.596309Z",
    "last_attempt_status": "success",
    "last_attempt_reason": null,
    "cadence_minutes": 2880,
    "grace_minutes": 180,
    "timezone": "America/Chicago",
    "archived": false,
    "source_count": 5,
    "row_count": 5,
    "quality_counts": {
      "big_box_public_price": 1,
      "manufacturer_direct_reference": 1,
      "member_only": 2,
      "out_of_stock": 1
    },
    "rendered_at_utc": null,
    "published_at_utc": null
  },
  "targets": [
    {
      "id": "ps5",
      "label": "PS5",
      "target": "PlayStation 5 console",
      "rules": [
        "Prefer standard PS5 Disc or Digital console from an authorized big-box retailer.",
        "Bundles are allowed when the bundle value is clear.",
        "Marketplace sellers, scalper pricing, PS5 Pro, refurb, and open-box rows are warnings, not default best buys."
      ]
    },
    {
      "id": "tv",
      "label": "65-inch TV",
      "target": "60-70 inch mid-quality 4K smart TV",
      "rules": [
        "Default to 65 inches.",
        "Prefer mainstream mid-quality models such as QLED, Mini LED, or strong value 4K sets.",
        "Avoid no-name marketplace rows and entry-tier TVs unless the price is clearly worth the tradeoff."
      ]
    }
  ],
  "items": [
    {
      "target_id": "ps5",
      "retailer": "GameStop",
      "brand": "Sony",
      "model": "PlayStation 5 Console",
      "product_name": "Sony PlayStation 5 Console",
      "price": 549.99,
      "url": "https://www.gamestop.com/consoles-hardware/playstation-5/consoles/products/sony-playstation-5-console/229025.html",
      "stock_status": "Public price displayed; store-specific stock not selected",
      "pickup_delivery": "Live search showed ship-to-home and store-pickup controls; confirm Houston store availability before buying.",
      "evidence_class": "big_box_public_price",
      "condition": "new",
      "evidence_text": "Live GameStop search on July 21 displayed Sony PlayStation 5 Console at $549.99; the page offered delivery and pickup selection controls.",
      "captured_at": "2026-07-21T11:04:07Z",
      "id": "ps5-gamestop-playstation-5-console",
      "warnings": []
    },
    {
      "target_id": "ps5",
      "retailer": "PlayStation Direct",
      "brand": "Sony",
      "model": "PlayStation 5 Digital Edition 825 GB",
      "product_name": "PlayStation 5 Digital Edition Console - 825 GB",
      "price": 599.0,
      "url": "https://direct.playstation.com/en-us/buy-consoles/playstation5-digital-edition-console-825-gb",
      "stock_status": "Public catalog price displayed; final availability requires an active session",
      "pickup_delivery": "PlayStation Direct page states free standard delivery; no Houston pickup path shown.",
      "evidence_class": "manufacturer_direct_reference",
      "condition": "new",
      "evidence_text": "Live PlayStation Direct PS5 catalog displayed the 825 GB Digital Edition Console at $599.00; the page also displayed a session-timeout sign-in dialog, so checkout availability was not confirmed.",
      "captured_at": "2026-07-21T11:04:07Z",
      "id": "ps5-playstation-direct-playstation-5-digital-edition-825-gb",
      "warnings": [
        "manufacturer-direct reference"
      ]
    },
    {
      "target_id": "ps5",
      "retailer": "Best Buy",
      "brand": "Sony Interactive Entertainment",
      "model": "1000039671",
      "product_name": "PlayStation 5 Slim Console",
      "price": 549.99,
      "url": "https://www.bestbuy.com/product/playstation-5-slim-console-playstation-5/6566039",
      "stock_status": "Unavailable at the page's selected location",
      "pickup_delivery": "No current buy path shown on the live product page; confirm Houston availability before buying.",
      "evidence_class": "out_of_stock",
      "condition": "new",
      "evidence_text": "Live Best Buy product page displayed PlayStation 5 Slim Console model 1000039671 at $549.99, sold by Best Buy, with its purchase control marked Unavailable.",
      "captured_at": "2026-07-21T11:04:07Z",
      "id": "ps5-best-buy-1000039671",
      "warnings": [
        "out of stock"
      ]
    },
    {
      "target_id": "tv",
      "retailer": "Sam's Club",
      "brand": "VIZIO",
      "model": "Quantum Series",
      "product_name": "VIZIO 65-inch Class Quantum Series QLED Smart TV",
      "price": 328.0,
      "url": "https://www.samsclub.com/ip/VIZIO-65-Class-Quantum-Series-QLED-Smart-TV/13743012826?classType=REGULAR",
      "stock_status": "Available for shipping",
      "pickup_delivery": "Live Sam's Club listing showed shipping availability; confirm Houston pickup or delivery timing before buying.",
      "evidence_class": "member_only",
      "condition": "new",
      "size_inches": 65,
      "quality_tier": "mid",
      "evidence_text": "Live Sam's Club QLED TV results displayed the VIZIO 65-inch Quantum Series 4K QLED Smart TV at $328.00, with Add to Cart and Available for Shipping shown.",
      "captured_at": "2026-07-21T11:04:07Z",
      "id": "tv-sam-s-club-quantum-series",
      "warnings": [
        "member-only price"
      ]
    },
    {
      "target_id": "tv",
      "retailer": "Sam's Club",
      "brand": "Samsung",
      "model": "Q7FD",
      "product_name": "Samsung 65-inch Class Q7FD Series 4K QLED Smart TV",
      "price": 497.99,
      "url": "https://www.samsclub.com/ip/SAMSUNG-65-Class-Q7FD-Series-4K-QLED-Smart-TV/15567708318?classType=REGULAR",
      "stock_status": "Available for shipping",
      "pickup_delivery": "Live Sam's Club listing showed shipping availability; confirm Houston pickup or delivery timing before buying.",
      "evidence_class": "member_only",
      "condition": "new",
      "size_inches": 65,
      "quality_tier": "mid",
      "evidence_text": "Live Sam's Club QLED TV results displayed the Samsung 65-inch Q7FD Series 4K QLED Smart TV at $497.99, with Add to Cart and Available for Shipping shown.",
      "captured_at": "2026-07-21T11:04:07Z",
      "id": "tv-sam-s-club-q7fd",
      "warnings": [
        "member-only price"
      ]
    }
  ],
  "daily_brief": {
    "summary": "PS5: GameStop $549.99 for Sony PlayStation 5 Console. TV: Sam's Club $328 for VIZIO 65-inch Class Quantum Series QLED Smart TV.",
    "warnings": [
      "manufacturer-direct reference",
      "member-only price",
      "out of stock"
    ],
    "data_quality_gaps": [
      "Confirm final cart total, tax, pickup/delivery timing, and seller identity before buying.",
      "Member-only and cart-only prices are shown as warnings until checkout proof is visible."
    ]
  }
}
